bizhook/__init__.py
bizhook/exceptions.py
bizhook/export.py
bizhook/lua_components.zip
bizhook/memory.py
bizhook-1.2.1.dist-info/LICENSE
bizhook-1.2.1.dist-info/WHEEL
bizhook-1.2.1.dist-info/METADATA
bizhook-1.2.1.dist-info/RECORD
