Metadata-Version: 2.1
Name: bizhook
Version: 1.2.1
Summary: Communicate with the Bizhawk emulator via a Lua socket
Home-page: https://gitlab.com/thedisruptproject/bizhook
Author: Maximillian Strand
Author-email: maximillian.strand@protonmail.com
Requires-Python: >=3.9,<4.0
Classifier: Programming Language :: Python :: 3
Classifier: Programming Language :: Python :: 3.10
Classifier: Programming Language :: Python :: 3.9
Project-URL: Repository, https://gitlab.com/thedisruptproject/bizhook
